fortranformat/FortranRecordReader.py
fortranformat/FortranRecordWriter.py
fortranformat/__init__.py
fortranformat/_edit_descriptors.py
fortranformat/_exceptions.py
fortranformat/_input.py
fortranformat/_lexer.py
fortranformat/_misc.py
fortranformat/_output.py
fortranformat/_parser.py
fortranformat/check_version.txt
fortranformat/config.py
fortranformat-2.0.2.dist-info/LICENSE
fortranformat-2.0.2.dist-info/METADATA
fortranformat-2.0.2.dist-info/WHEEL
fortranformat-2.0.2.dist-info/RECORD
